simplecalcdoctest/__init__.py
simplecalcdoctest/simplecalc.py
simplecalcdoctest/simpleplot.py
simplecalcdoctest-0.1.0.dist-info/LICENSE
simplecalcdoctest-0.1.0.dist-info/METADATA
simplecalcdoctest-0.1.0.dist-info/WHEEL
simplecalcdoctest-0.1.0.dist-info/RECORD
